svim_asm/SVCandidate.py
svim_asm/SVIM_COLLECT.py
svim_asm/SVIM_COMBINE.py
svim_asm/SVIM_input_parsing.py
svim_asm/SVIM_inter.py
svim_asm/SVIM_intra.py
svim_asm/SVIM_plot.py
svim_asm/__init__.py
svim_asm-1.0.3.data/data/LICENSE
svim_asm-1.0.3.data/scripts/svim-asm
tests/__init__.py
tests/test_Collect.py
tests/test_Combine.py
tests/test_Signature.py
tests/test_clustering.py
tests/test_input_parsing.py
tests/test_inter.py
tests/test_intra.py
tests/test_satag.py
svim_asm-1.0.3.dist-info/LICENSE
svim_asm-1.0.3.dist-info/METADATA
svim_asm-1.0.3.dist-info/WHEEL
svim_asm-1.0.3.dist-info/top_level.txt
svim_asm-1.0.3.dist-info/RECORD
