Metadata-Version: 2.1
Name: svim-asm
Version: 1.0.3
Summary: A structural variant caller for genome-genome alignments.
Home-page: https://github.com/eldariont/svim-asm
Author: David Heller
Author-email: heller_d@molgen.mpg.de
License: GPLv3
Keywords: svim-asm SV assembly structural variation caller
Platform: UNKNOWN
Classifier: Development Status :: 5 - Production/Stable
Classifier: Environment :: Console
Classifier: Intended Audience :: Science/Research
Classifier: Topic :: Scientific/Engineering :: Bio-Informatics
Classifier: License :: OSI Approved :: GNU General Public License v3 (GPLv3)
Classifier: Programming Language :: Python :: 3.6
Requires-Dist: pysam
Requires-Dist: numpy
Requires-Dist: scipy
Requires-Dist: matplotlib
Requires-Dist: edlib
